bids_validator/__init__.py
bids_validator/_version.py
bids_validator/bids_validator.py
bids_validator/test_bids_validator.py
bids_validator/rules/associated_data_rules.json
bids_validator/rules/file_level_rules.json
bids_validator/rules/phenotypic_rules.json
bids_validator/rules/session_level_rules.json
bids_validator/rules/subject_level_rules.json
bids_validator/rules/top_level_rules.json
bids_validator/tsv/non_custom_columns.json
bids_validator-1.14.7.post0.dist-info/LICENSE
bids_validator-1.14.7.post0.dist-info/METADATA
bids_validator-1.14.7.post0.dist-info/WHEEL
bids_validator-1.14.7.post0.dist-info/top_level.txt
bids_validator-1.14.7.post0.dist-info/RECORD
