Metadata-Version: 2.1
Name: bids-validator
Version: 1.14.7.post0
Summary: Validator for the Brain Imaging Data Structure
Author-email: PyBIDS developers <bids-discussion@googlegroups.com>
License: MIT License
Project-URL: Homepage, https://github.com/bids-standard/bids-validator
Classifier: Development Status :: 3 - Alpha
Classifier: Environment :: Console
Classifier: Intended Audience :: Science/Research
Classifier: License :: OSI Approved :: MIT License
Classifier: Operating System :: OS Independent
Classifier: Programming Language :: Python
Classifier: Topic :: Scientific/Engineering
Requires-Python: >=3.8
License-File: LICENSE
Requires-Dist: bidsschematools>=0.10
